doc2vision/__init__.py
doc2vision/converter.py
doc2vision-0.1.1.dist-info/METADATA
doc2vision-0.1.1.dist-info/WHEEL
doc2vision-0.1.1.dist-info/top_level.txt
doc2vision-0.1.1.dist-info/RECORD
